mobio/__init__.py
mobio/libs/__init__.py
mobio/libs/filetypes/__init__.py
mobio/libs/filetypes/common.py
mobio/libs/filetypes/custom_mimetypes.py
mobio/libs/filetypes/file.py
mobio/libs/filetypes/file_signature.json
mobio/libs/filetypes/utils.py
m_filetypes-0.0.9.dist-info/LICENSE
m_filetypes-0.0.9.dist-info/METADATA
m_filetypes-0.0.9.dist-info/WHEEL
m_filetypes-0.0.9.dist-info/top_level.txt
m_filetypes-0.0.9.dist-info/RECORD
