Metadata-Version: 2.1
Name: m-filetypes
Version: 0.0.9
Summary: Libs check filetype
Author: MOBIO
Author-email: contact@mobio.vn
Classifier: Programming Language :: Python
Classifier: Programming Language :: Python :: 3.8
Classifier: Programming Language :: Python :: 3.9
License-File: LICENSE
